LICENSE
MANIFEST.in
README.md
requirements.txt
setup.cfg
setup.py
src/cryptlex_python_sdk.egg-info/PKG-INFO
src/cryptlex_python_sdk.egg-info/SOURCES.txt
src/cryptlex_python_sdk.egg-info/dependency_links.txt
src/cryptlex_python_sdk.egg-info/requires.txt
src/cryptlex_python_sdk.egg-info/top_level.txt
src/cryptlex_web_api_client/__init__.py
src/cryptlex_web_api_client/client.py
src/cryptlex_web_api_client/types.py
src/cryptlex_web_api_client/api/__init__.py
src/cryptlex_web_api_client/api/accounts/__init__.py
src/cryptlex_web_api_client/api/accounts/getv3accountsid.py
src/cryptlex_web_api_client/api/accounts/getv_3_accountsloginsamlcompany_id.py
src/cryptlex_web_api_client/api/accounts/patchv3accountsid.py
src/cryptlex_web_api_client/api/accounts/postv3accounts.py
src/cryptlex_web_api_client/api/accounts/postv3accountslogin.py
src/cryptlex_web_api_client/api/accounts/postv3accountslogin_google.py
src/cryptlex_web_api_client/api/accounts/postv3accountsloginsamlverify.py
src/cryptlex_web_api_client/api/accounts/postv3accountsreset_password_request.py
src/cryptlex_web_api_client/api/accounts/postv_3_accountsloginsamlcompany_idacs.py
src/cryptlex_web_api_client/api/accounts/putv3accountsidplan.py
src/cryptlex_web_api_client/api/accounts/putv3accountsidstatus.py
src/cryptlex_web_api_client/api/activation_logs/__init__.py
src/cryptlex_web_api_client/api/activation_logs/getv3activation_logs.py
src/cryptlex_web_api_client/api/activation_logs/getv3activation_logsid.py
src/cryptlex_web_api_client/api/activations/__init__.py
src/cryptlex_web_api_client/api/activations/deletev3activationsid.py
src/cryptlex_web_api_client/api/activations/getv3activations.py
src/cryptlex_web_api_client/api/activations/getv3activationsid.py
src/cryptlex_web_api_client/api/activations/patchv3activationsid.py
src/cryptlex_web_api_client/api/activations/postv3activations.py
src/cryptlex_web_api_client/api/activations/postv3activationsmeter_attributesid.py
src/cryptlex_web_api_client/api/activations/postv3activationsoffline_activate.py
src/cryptlex_web_api_client/api/activations/postv3activationsoffline_deactivate.py
src/cryptlex_web_api_client/api/analytics/__init__.py
